{
  "stage": 2,
  "best_checkpoint": "/mnt/PRO6000_disk/swd/ele_servo_new/experiments_smoke_20260316/models/exp1_decoupled_v8_ablation_vibration_enhanced/A4_no_vibration/stage2_signal_fusion/best.pt",
  "best_val_scenario_accuracy": 0.9365003580806875,
  "train_scenario_accuracy": 0.9853775755406718,
  "val_scenario_accuracy": 0.9365003580806875,
  "test_scenario_accuracy": 0.9353067557889712,
  "train_loss": 0.38133382024718204,
  "val_loss": 0.5071700712495614,
  "test_loss": 0.5139030395558126,
  "train_quality_loss": 1.290316322268155e-10,
  "val_quality_loss": 1.203099684947388e-10,
  "test_quality_loss": 1.2789481837712088e-10,
  "strict_modalities": {
    "pos": [
      "theta_meas_deg",
      "theta_motor_meas_deg",
      "omega_motor_meas_deg_s",
      "encoder_count",
      "motor_encoder_count"
    ],
    "electrical": [
      "current_meas_a",
      "current_d_meas_a",
      "current_q_meas_a",
      "bus_current_meas_a",
      "phase_voltage_a_meas_v",
      "phase_voltage_b_meas_v",
      "phase_voltage_c_meas_v",
      "voltage_meas_v",
      "available_bus_voltage_v"
    ],
    "thermal": [
      "winding_temp_c",
      "housing_temp_c"
    ],
    "vibration": [
      "vibration_accel_mps2"
    ]
  },
  "feature_mode": {
    "name": "modality_tf",
    "description": "Apply modality-specific time/frequency feature augmentation before training.",
    "algorithms": {
      "pos": [
        "first_difference",
        "second_difference",
        "rolling_rms_velocity"
      ],
      "electrical": [
        "rolling_rms",
        "fft_low_mid_high_band_energy"
      ],
      "thermal": [
        "raw_only"
      ],
      "vibration": [
        "envelope",
        "highpass_residual",
        "spectral_centroid"
      ]
    },
    "channel_expansion": {
      "X_pos": {
        "original_dim": 5,
        "augmented_dim": 20,
        "feature_groups": [
          "raw",
          "delta",
          "delta2",
          "delta_rms"
        ]
      },
      "X_electrical": {
        "original_dim": 9,
        "augmented_dim": 45,
        "feature_groups": [
          "raw",
          "rolling_rms",
          "fft_band_energy_low_mid_high"
        ]
      },
      "X_thermal": {
        "original_dim": 2,
        "augmented_dim": 2,
        "feature_groups": [
          "raw"
        ]
      },
      "X_vibration": {
        "original_dim": 1,
        "augmented_dim": 4,
        "feature_groups": [
          "raw",
          "envelope",
          "highpass_residual",
          "spectral_centroid"
        ]
      }
    }
  },
  "thermal_feature_policy": "raw_only",
  "quality_aware_fusion": {
    "enabled": true,
    "quality_hidden_dim": 128,
    "quality_drop_prob": 0.0,
    "quality_min_gate": 0.1,
    "lambda_quality": 0.1
  },
  "split": {
    "mode": "random_stratified",
    "train": 19559,
    "val": 4189,
    "test": 4189,
    "val_ratio": 0.15,
    "test_ratio": 0.15
  },
  "history": [
    {
      "epoch": 1,
      "loss": 0.7129548884491301,
      "scenario_accuracy": 0.8597065289636484,
      "align_loss": 0.0,
      "quality_loss": 1.0180233222642643e-09,
      "val_loss": 0.7033067530736515,
      "val_scenario_accuracy": 0.8570064454523753,
      "val_align_loss": 0.0,
      "val_quality_loss": 9.513712516204612e-11
    },
    {
      "epoch": 2,
      "loss": 0.6317268859798286,
      "scenario_accuracy": 0.8875198118513217,
      "align_loss": 0.0,
      "quality_loss": 2.3384255064961774e-10,
      "val_loss": 0.6490502176491962,
      "val_scenario_accuracy": 0.8775364048698974,
      "val_align_loss": 0.0,
      "val_quality_loss": 1.4009024262271902e-10
    },
    {
      "epoch": 3,
      "loss": 0.5962225721288211,
      "scenario_accuracy": 0.8994836136816811,
      "align_loss": 0.0,
      "quality_loss": 2.2916035265804563e-10,
      "val_loss": 0.682866036166266,
      "val_scenario_accuracy": 0.8732394366197183,
      "val_align_loss": 0.0,
      "val_quality_loss": 1.1395144869870757e-10
    },
    {
      "epoch": 4,
      "loss": 0.5810724674171267,
      "scenario_accuracy": 0.9087887928830717,
      "align_loss": 0.0,
      "quality_loss": 2.181544138906584e-10,
      "val_loss": 0.6325204965748973,
      "val_scenario_accuracy": 0.8873239436619719,
      "val_align_loss": 0.0,
      "val_quality_loss": 1.2541830840514218e-10
    },
    {
      "epoch": 5,
      "loss": 0.5600400559649499,
      "scenario_accuracy": 0.9158443683214889,
      "align_loss": 0.0,
      "quality_loss": 5.716132881092406e-10,
      "val_loss": 0.6022032886053447,
      "val_scenario_accuracy": 0.8963953210790164,
      "val_align_loss": 0.0,
      "val_quality_loss": 6.679425835043024e-11
    },
    {
      "epoch": 6,
      "loss": 0.550169117483992,
      "scenario_accuracy": 0.9192699013241986,
      "align_loss": 0.0,
      "quality_loss": 1.1859133006135357e-10,
      "val_loss": 0.6056359958808045,
      "val_scenario_accuracy": 0.8911434709954643,
      "val_align_loss": 0.0,
      "val_quality_loss": 5.033380842487524e-11
    },
    {
      "epoch": 7,
      "loss": 0.5268596649532565,
      "scenario_accuracy": 0.9293419908993302,
      "align_loss": 0.0,
      "quality_loss": 1.7636080192208492e-10,
      "val_loss": 0.6385423367832805,
      "val_scenario_accuracy": 0.8863690618285988,
      "val_align_loss": 0.0,
      "val_quality_loss": 6.059812823718677e-11
    },
    {
      "epoch": 8,
      "loss": 0.5201118485414029,
      "scenario_accuracy": 0.9324607597525436,
      "align_loss": 0.0,
      "quality_loss": 1.451622203693686e-10,
      "val_loss": 0.5613708317521706,
      "val_scenario_accuracy": 0.908808784912867,
      "val_align_loss": 0.0,
      "val_quality_loss": 9.316708602457091e-11
    },
    {
      "epoch": 9,
      "loss": 0.5066637918288323,
      "scenario_accuracy": 0.9388005521754691,
      "align_loss": 0.0,
      "quality_loss": 1.2569037985847216e-10,
      "val_loss": 0.6023543159043655,
      "val_scenario_accuracy": 0.9026020529959418,
      "val_align_loss": 0.0,
      "val_quality_loss": 7.41401799949224e-11
    },
    {
      "epoch": 10,
      "loss": 0.4982335545045295,
      "scenario_accuracy": 0.9407433917889463,
      "align_loss": 0.0,
      "quality_loss": 1.4515563653155976e-10,
      "val_loss": 0.5588367533558563,
      "val_scenario_accuracy": 0.9102411076629268,
      "val_align_loss": 0.0,
      "val_quality_loss": 5.767798588193751e-11
    },
    {
      "epoch": 11,
      "loss": 0.4869598849089491,
      "scenario_accuracy": 0.9440666700751572,
      "align_loss": 0.0,
      "quality_loss": 1.5534206905057227e-10,
      "val_loss": 0.5636470184658557,
      "val_scenario_accuracy": 0.9092862258295535,
      "val_align_loss": 0.0,
      "val_quality_loss": 1.0976606616360932e-10
    },
    {
      "epoch": 12,
      "loss": 0.4783629439159785,
      "scenario_accuracy": 0.948770387034102,
      "align_loss": 0.0,
      "quality_loss": 2.9751582953335547e-10,
      "val_loss": 0.5901860029081594,
      "val_scenario_accuracy": 0.9114347099546432,
      "val_align_loss": 0.0,
      "val_quality_loss": 8.895912696040371e-11
    },
    {
      "epoch": 13,
      "loss": 0.4678866362802102,
      "scenario_accuracy": 0.9524004294698093,
      "align_loss": 0.0,
      "quality_loss": 1.5784536154677123e-10,
      "val_loss": 0.5379029925753434,
      "val_scenario_accuracy": 0.9233707328718072,
      "val_align_loss": 0.0,
      "val_quality_loss": 8.464438660009269e-11
    },
    {
      "epoch": 14,
      "loss": 0.45922576045751073,
      "scenario_accuracy": 0.9563883634132624,
      "align_loss": 0.0,
      "quality_loss": 2.0556824944902394e-10,
      "val_loss": 0.5550575319594886,
      "val_scenario_accuracy": 0.9159703986631654,
      "val_align_loss": 0.0,
      "val_quality_loss": 7.4260138698454e-11
    },
    {
      "epoch": 15,
      "loss": 0.4500169434962606,
      "scenario_accuracy": 0.9594048775499769,
      "align_loss": 0.0,
      "quality_loss": 1.2268105310907011e-10,
      "val_loss": 0.5442418600073519,
      "val_scenario_accuracy": 0.9219384101217475,
      "val_align_loss": 0.0,
      "val_quality_loss": 8.251281420502449e-11
    },
    {
      "epoch": 16,
      "loss": 0.44383033176184955,
      "scenario_accuracy": 0.961449971879953,
      "align_loss": 0.0,
      "quality_loss": 1.4160179227593557e-10,
      "val_loss": 0.5294804970613098,
      "val_scenario_accuracy": 0.9295774647887324,
      "val_align_loss": 0.0,
      "val_quality_loss": 8.617908156195294e-11
    },
    {
      "epoch": 17,
      "loss": 0.4448914133098765,
      "scenario_accuracy": 0.9600184058489698,
      "align_loss": 0.0,
      "quality_loss": 2.0873515537842825e-10,
      "val_loss": 0.5071700712495614,
      "val_scenario_accuracy": 0.9365003580806875,
      "val_align_loss": 0.0,
      "val_quality_loss": 1.203099684947388e-10
    },
    {
      "epoch": 18,
      "loss": 0.43256134723335865,
      "scenario_accuracy": 0.9661025614806483,
      "align_loss": 0.0,
      "quality_loss": 1.7014814526665417e-10,
      "val_loss": 0.5481347733933819,
      "val_scenario_accuracy": 0.9271902602052996,
      "val_align_loss": 0.0,
      "val_quality_loss": 8.716581509090551e-11
    },
    {
      "epoch": 19,
      "loss": 0.4258124168357135,
      "scenario_accuracy": 0.9680454010941255,
      "align_loss": 0.0,
      "quality_loss": 1.748683350148285e-10,
      "val_loss": 0.5317711998181857,
      "val_scenario_accuracy": 0.928383862497016,
      "val_align_loss": 0.0,
      "val_quality_loss": 3.613913954789406e-11
    },
    {
      "epoch": 20,
      "loss": 0.42859287729194556,
      "scenario_accuracy": 0.966204816197147,
      "align_loss": 0.0,
      "quality_loss": 5.294109101403461e-11,
      "val_loss": 0.51994911383319,
      "val_scenario_accuracy": 0.9302936261637622,
      "val_align_loss": 0.0,
      "val_quality_loss": 4.339345731737557e-11
    }
  ]
}